git_branch_manager/__init__.py
git_branch_manager/branch_operations.py
git_branch_manager/main.py
git_branch_manager/repository_operations.py
git_branch_manager/summary_printer.py
git_branch_manager-0.1.0.dist-info/LICENSE
git_branch_manager-0.1.0.dist-info/METADATA
git_branch_manager-0.1.0.dist-info/WHEEL
git_branch_manager-0.1.0.dist-info/entry_points.txt
git_branch_manager-0.1.0.dist-info/top_level.txt
git_branch_manager-0.1.0.dist-info/RECORD
