Metadata-Version: 2.1
Name: git-branch-manager
Version: 0.1.0
Summary: A tool to manage Git branches across repositories.
Home-page: https://github.com/DahalRocks/git_branch_manager
Author: Dhruba Dahal
Author-email: dhruba.dahal03@gmail.com
License: UNKNOWN
Platform: UNKNOWN
Classifier: Programming Language :: Python :: 3
Classifier: License :: OSI Approved :: MIT License
Classifier: Operating System :: OS Independent
Requires-Python: >=3.7
License-File: LICENSE
Requires-Dist: PyYAML>=6.0
